opyngpt/__init__.py
opyngpt/chat.py
opyngpt-0.4.0.dist-info/LICENSE
opyngpt-0.4.0.dist-info/METADATA
opyngpt-0.4.0.dist-info/WHEEL
opyngpt-0.4.0.dist-info/entry_points.txt
opyngpt-0.4.0.dist-info/top_level.txt
opyngpt-0.4.0.dist-info/RECORD
