Metadata-Version: 2.1
Name: opyngpt
Version: 0.4.0
Summary: Supercharge your projects with LLMs. No API keys required.
Author: Anas Khan
License-File: LICENSE
Requires-Dist: requests
